{
  "chandana@gmail.com_team": {
    "leader": "chandana@gmail.com",
    "members": [
      {
        "name": "sannith",
        "gitlab_username": "sanny1724",
        "added_at": "2025-06-06T14:53:14.775044"
      }
    ],
    "created_at": "2025-06-06T14:51:18.515360"
  },
  "sanny@gmail.com_team": {
    "leader": "sanny@gmail.com",
    "members": [],
    "created_at": "2025-06-07T12:34:21.719131"
  },
  "sanny1@gmail.com_team": {
    "leader": "sanny1@gmail.com",
    "members": [],
    "created_at": "2025-06-07T12:54:32.996311"
  }
}